chainingiterator/__init__.py
chainingiterator/chainingiterator.py
chainingiterator/py.typed
chainingiterator-0.2.4.dist-info/LICENSE
chainingiterator-0.2.4.dist-info/METADATA
chainingiterator-0.2.4.dist-info/WHEEL
chainingiterator-0.2.4.dist-info/RECORD
